README.md
README.rst
setup.py
cfnlint/__init__.py
cfnlint/linter.py
cfnlint.egg-info/PKG-INFO
cfnlint.egg-info/SOURCES.txt
cfnlint.egg-info/dependency_links.txt
cfnlint.egg-info/entry_points.txt
cfnlint.egg-info/not-zip-safe
cfnlint.egg-info/requires.txt
cfnlint.egg-info/top_level.txt
cfnlint/cli/__init__.py
cfnlint/cli/cli.py
cfnlint/core/BaseYamlLinter.py
cfnlint/core/__init__.py
cfnlint/core/linter.py
cfnlint/core/lintrules.py